{
  "credentials": {
  "peers": [
    {
      "discovery_host": "0d711df2d6e4430e8b7bc6b7195d161f-vp2.us.blockchain.ibm.com",
      "discovery_port": 30004,
      "api_host": "0d711df2d6e4430e8b7bc6b7195d161f-vp2.us.blockchain.ibm.com",
      "api_port_tls": 5004,
      "api_port": 5004,
      "event_host": "0d711df2d6e4430e8b7bc6b7195d161f-vp2.us.blockchain.ibm.com",
      "event_port": 31004,
      "type": "peer",
      "network_id": "0d711df2d6e4430e8b7bc6b7195d161f",
      "container_id": "9bc7392f7e5b6d4874813115e7786d3db4206515a7c28530ad5eb30723d59a41",
      "id": "0d711df2d6e4430e8b7bc6b7195d161f-vp2",
      "api_url": "http://0d711df2d6e4430e8b7bc6b7195d161f-vp2.us.blockchain.ibm.com:5004"
    },
    {
      "discovery_host": "0d711df2d6e4430e8b7bc6b7195d161f-vp0.us.blockchain.ibm.com",
      "discovery_port": 30004,
      "api_host": "0d711df2d6e4430e8b7bc6b7195d161f-vp0.us.blockchain.ibm.com",
      "api_port_tls": 5004,
      "api_port": 5004,
      "event_host": "0d711df2d6e4430e8b7bc6b7195d161f-vp0.us.blockchain.ibm.com",
      "event_port": 31004,
      "type": "peer",
      "network_id": "0d711df2d6e4430e8b7bc6b7195d161f",
      "container_id": "94421c501aa84f29ec00fb32f479486294ef82e63cba1f6108ac25613b735125",
      "id": "0d711df2d6e4430e8b7bc6b7195d161f-vp0",
      "api_url": "http://0d711df2d6e4430e8b7bc6b7195d161f-vp0.us.blockchain.ibm.com:5004"
    },
    {
      "discovery_host": "0d711df2d6e4430e8b7bc6b7195d161f-vp1.us.blockchain.ibm.com",
      "discovery_port": 30004,
      "api_host": "0d711df2d6e4430e8b7bc6b7195d161f-vp1.us.blockchain.ibm.com",
      "api_port_tls": 5004,
      "api_port": 5004,
      "event_host": "0d711df2d6e4430e8b7bc6b7195d161f-vp1.us.blockchain.ibm.com",
      "event_port": 31004,
      "type": "peer",
      "network_id": "0d711df2d6e4430e8b7bc6b7195d161f",
      "container_id": "0639986d105f15705fcb09f909d56208ba095bea8f7a600b710f5cfacd131821",
      "id": "0d711df2d6e4430e8b7bc6b7195d161f-vp1",
      "api_url": "http://0d711df2d6e4430e8b7bc6b7195d161f-vp1.us.blockchain.ibm.com:5004"
    },
    {
      "discovery_host": "0d711df2d6e4430e8b7bc6b7195d161f-vp3.us.blockchain.ibm.com",
      "discovery_port": 30004,
      "api_host": "0d711df2d6e4430e8b7bc6b7195d161f-vp3.us.blockchain.ibm.com",
      "api_port_tls": 5004,
      "api_port": 5004,
      "event_host": "0d711df2d6e4430e8b7bc6b7195d161f-vp3.us.blockchain.ibm.com",
      "event_port": 31004,
      "type": "peer",
      "network_id": "0d711df2d6e4430e8b7bc6b7195d161f",
      "container_id": "a15ab7b129c13b2a21dd2811f5b84f07fb7b40d9dd3d7b19204d5c7a4cf01a7c",
      "id": "0d711df2d6e4430e8b7bc6b7195d161f-vp3",
      "api_url": "http://0d711df2d6e4430e8b7bc6b7195d161f-vp3.us.blockchain.ibm.com:5004"
    }
  ],
  "ca": {
    "0d711df2d6e4430e8b7bc6b7195d161f-ca": {
      "url": "0d711df2d6e4430e8b7bc6b7195d161f-ca.us.blockchain.ibm.com:30004",
      "discovery_host": "0d711df2d6e4430e8b7bc6b7195d161f-ca.us.blockchain.ibm.com",
      "discovery_port": 30004,
      "api_host": "0d711df2d6e4430e8b7bc6b7195d161f-ca.us.blockchain.ibm.com",
      "api_port_tls": 30004,
      "api_port": 30004,
      "type": "ca",
      "network_id": "0d711df2d6e4430e8b7bc6b7195d161f",
      "container_id": "b4733cfce85b6652de338405e571e11643f5570e6bff5506e516e817c7bf9f6f"
    }
  },
  "users": [
    {
      "enrollId": "admin",
      "enrollSecret": "6c8a51fb17",
      "affiliation": "group1",
      "username": "admin",
      "secret": "6c8a51fb17"
    },
    {
      "enrollId": "WebAppAdmin",
      "enrollSecret": "0d670594a8",
      "affiliation": "group1",
      "username": "WebAppAdmin",
      "secret": "0d670594a8"
    },
    {
      "enrollId": "user_type1_0",
      "enrollSecret": "910bc5c658",
      "affiliation": "group1",
      "username": "user_type1_0",
      "secret": "910bc5c658"
    },
    {
      "enrollId": "user_type1_1",
      "enrollSecret": "bc6e1f896c",
      "affiliation": "group1",
      "username": "user_type1_1",
      "secret": "bc6e1f896c"
    },
    {
      "enrollId": "user_type1_2",
      "enrollSecret": "8dd5eb1041",
      "affiliation": "group1",
      "username": "user_type1_2",
      "secret": "8dd5eb1041"
    },
    {
      "enrollId": "user_type1_3",
      "enrollSecret": "a732693eb9",
      "affiliation": "group1",
      "username": "user_type1_3",
      "secret": "a732693eb9"
    },
    {
      "enrollId": "user_type1_4",
      "enrollSecret": "2a02029f0a",
      "affiliation": "group1",
      "username": "user_type1_4",
      "secret": "2a02029f0a"
    },
    {
      "enrollId": "user_type2_0",
      "enrollSecret": "031f9d88e1",
      "affiliation": "group1",
      "username": "user_type2_0",
      "secret": "031f9d88e1"
    },
    {
      "enrollId": "user_type2_1",
      "enrollSecret": "64acc261af",
      "affiliation": "group1",
      "username": "user_type2_1",
      "secret": "64acc261af"
    },
    {
      "enrollId": "user_type2_2",
      "enrollSecret": "d92df1dceb",
      "affiliation": "group1",
      "username": "user_type2_2",
      "secret": "d92df1dceb"
    },
    {
      "enrollId": "user_type2_3",
      "enrollSecret": "a4b75bdaae",
      "affiliation": "group1",
      "username": "user_type2_3",
      "secret": "a4b75bdaae"
    },
    {
      "enrollId": "user_type2_4",
      "enrollSecret": "70a7036a2c",
      "affiliation": "group1",
      "username": "user_type2_4",
      "secret": "70a7036a2c"
    },
    {
      "enrollId": "user_type4_0",
      "enrollSecret": "1929d0f62e",
      "affiliation": "group1",
      "username": "user_type4_0",
      "secret": "1929d0f62e"
    },
    {
      "enrollId": "user_type4_1",
      "enrollSecret": "fba031bd9a",
      "affiliation": "group1",
      "username": "user_type4_1",
      "secret": "fba031bd9a"
    },
    {
      "enrollId": "user_type4_2",
      "enrollSecret": "99d08a0817",
      "affiliation": "group1",
      "username": "user_type4_2",
      "secret": "99d08a0817"
    },
    {
      "enrollId": "user_type4_3",
      "enrollSecret": "82fd5e9ad4",
      "affiliation": "group1",
      "username": "user_type4_3",
      "secret": "82fd5e9ad4"
    },
    {
      "enrollId": "user_type4_4",
      "enrollSecret": "798976f45d",
      "affiliation": "group1",
      "username": "user_type4_4",
      "secret": "798976f45d"
    },
    {
      "enrollId": "user_type8_0",
      "enrollSecret": "12fec89b59",
      "affiliation": "group1",
      "username": "user_type8_0",
      "secret": "12fec89b59"
    },
    {
      "enrollId": "user_type8_1",
      "enrollSecret": "406ae437fa",
      "affiliation": "group1",
      "username": "user_type8_1",
      "secret": "406ae437fa"
    },
    {
      "enrollId": "user_type8_2",
      "enrollSecret": "454f2f9283",
      "affiliation": "group1",
      "username": "user_type8_2",
      "secret": "454f2f9283"
    },
    {
      "enrollId": "user_type8_3",
      "enrollSecret": "8890776311",
      "affiliation": "group1",
      "username": "user_type8_3",
      "secret": "8890776311"
    },
    {
      "enrollId": "user_type8_4",
      "enrollSecret": "21af1ee577",
      "affiliation": "group1",
      "username": "user_type8_4",
      "secret": "21af1ee577"
    }
  ],
  "cert": "https://blockchain-certs.mybluemix.net/us.blockchain.ibm.com.cert",
  "cert_path": "/certs/peer/cert.pem"
}
}
